uth.py
uth-1.1.1.dist-info/LICENSE.txt
uth-1.1.1.dist-info/METADATA
uth-1.1.1.dist-info/WHEEL
uth-1.1.1.dist-info/top_level.txt
uth-1.1.1.dist-info/RECORD
