Metadata-Version: 2.1
Name: uth
Version: 1.1.1
Summary: Unit test helpers
Home-page: https://github.com/janneronkko/uth
Author: Janne Rönkkö
Author-email: janne.ronkko@iki.fi
License: MIT
Keywords: unittest mock patch
Platform: UNKNOWN
Classifier: Development Status :: 5 - Production/Stable
Classifier: Intended Audience :: Developers
Classifier: License :: OSI Approved :: MIT License
Classifier: Operating System :: OS Independent
Classifier: Programming Language :: Python :: 3.4
Classifier: Programming Language :: Python :: 3.5
Classifier: Programming Language :: Python :: 3.6
Classifier: Programming Language :: Python :: 3.7
Classifier: Programming Language :: Python :: 3.8
Classifier: Topic :: Software Development :: Testing
Requires-Python: >=3.4
